py_pidx/__init__.py
py_pidx/controller.py
py_pidx/gain_scheduler.py
py_pidx-1.1.1.dist-info/METADATA
py_pidx-1.1.1.dist-info/WHEEL
py_pidx-1.1.1.dist-info/top_level.txt
py_pidx-1.1.1.dist-info/RECORD
