Metadata-Version: 2.4
Name: py_pidx
Version: 1.1.1
Summary: py_pidx: A Python package for PID control.
Home-page: https://github.com/mehrabmahdian/py_pidx
Author: Mehrab Mahdian
Author-email: Mehrab Mahdian <memahdian@outlook.com>
Project-URL: Homepage, https://github.com/mehrabmahdian/py_pidx
Requires-Python: >=3.8
Dynamic: author
Dynamic: home-page
Dynamic: requires-python
